ambientctl/__init__.py
ambientctl/config.py
ambientctl/main.py
ambientctl/commands/__init__.py
ambientctl/commands/auth.py
ambientctl/commands/daemon.py
ambientctl/commands/data.py
ambientctl/commands/health.py
ambientctl/commands/onboarding.py
ambientctl/commands/ping.py
ambientctl/commands/software.py
ambientctl/models/__init__.py
ambientctl/models/system_service.py
ambientctl/templates/ambient_edge_server.service.jinja2
ambientctl-1.8.0.dist-info/METADATA
ambientctl-1.8.0.dist-info/WHEEL
ambientctl-1.8.0.dist-info/entry_points.txt
ambientctl-1.8.0.dist-info/top_level.txt
ambientctl-1.8.0.dist-info/RECORD
