Metadata-Version: 2.1
Name: ambientctl
Version: 1.8.0
Summary: Ambient Edge Client Command Line Interface
Author: Ambient Labs Computing - An Edge Compute Company
Author-email: jose@ambientlabscomputing.com
Requires-Dist: requests==2.31.0
Requires-Dist: tqdm==4.66.4
Requires-Dist: pydantic-settings==2.3.1
Requires-Dist: rich==13.7.1
Requires-Dist: click==8.1.7
Requires-Dist: file-read-backwards==3.1.0
